wotpy2/__init__.py
wotpy2/__version__.py
wotpy2/support.py
wotpy2/codecs/__init__.py
wotpy2/codecs/base.py
wotpy2/codecs/enums.py
wotpy2/codecs/json_codec.py
wotpy2/codecs/text.py
wotpy2/protocols/__init__.py
wotpy2/protocols/client.py
wotpy2/protocols/enums.py
wotpy2/protocols/exceptions.py
wotpy2/protocols/refs.py
wotpy2/protocols/server.py
wotpy2/protocols/utils.py
wotpy2/protocols/coap/__init__.py
wotpy2/protocols/coap/authenticator.py
wotpy2/protocols/coap/client.py
wotpy2/protocols/coap/credential.py
wotpy2/protocols/coap/enums.py
wotpy2/protocols/coap/server.py
wotpy2/protocols/coap/resources/__init__.py
wotpy2/protocols/coap/resources/action.py
wotpy2/protocols/coap/resources/event.py
wotpy2/protocols/coap/resources/property.py
wotpy2/protocols/coap/resources/utils.py
wotpy2/protocols/http/__init__.py
wotpy2/protocols/http/authenticator.py
wotpy2/protocols/http/client.py
wotpy2/protocols/http/credential.py
wotpy2/protocols/http/enums.py
wotpy2/protocols/http/server.py
wotpy2/protocols/http/handlers/__init__.py
wotpy2/protocols/http/handlers/action.py
wotpy2/protocols/http/handlers/event.py
wotpy2/protocols/http/handlers/property.py
wotpy2/protocols/http/handlers/utils.py
wotpy2/protocols/mqtt/__init__.py
wotpy2/protocols/mqtt/client.py
wotpy2/protocols/mqtt/enums.py
wotpy2/protocols/mqtt/runner.py
wotpy2/protocols/mqtt/server.py
wotpy2/protocols/mqtt/handlers/__init__.py
wotpy2/protocols/mqtt/handlers/action.py
wotpy2/protocols/mqtt/handlers/base.py
wotpy2/protocols/mqtt/handlers/event.py
wotpy2/protocols/mqtt/handlers/ping.py
wotpy2/protocols/mqtt/handlers/property.py
wotpy2/protocols/mqtt/handlers/subs.py
wotpy2/protocols/ws/__init__.py
wotpy2/protocols/ws/client.py
wotpy2/protocols/ws/enums.py
wotpy2/protocols/ws/handler.py
wotpy2/protocols/ws/messages.py
wotpy2/protocols/ws/schemas.py
wotpy2/protocols/ws/server.py
wotpy2/protocols/zenoh/__init__.py
wotpy2/protocols/zenoh/client.py
wotpy2/protocols/zenoh/enums.py
wotpy2/protocols/zenoh/runner.py
wotpy2-0.1.0.dist-info/licenses/LICENSE
wotpy2-0.1.0.dist-info/METADATA
wotpy2-0.1.0.dist-info/WHEEL
wotpy2-0.1.0.dist-info/top_level.txt
wotpy2-0.1.0.dist-info/RECORD
