Metadata-Version: 2.4
Name: wotpy2
Version: 0.1.0
Summary: Python implementation of a W3C WoT Runtime and the WoT Scripting API
Author-email: Andres Garcia Mangas <andres.garcia@fundacionctic.org>
Maintainer-email: Nikos Filinis <nfilinis@netmode.ntua.gr>, Dimitris Spatharakis <dspatharakis@netmode.ntua.gr>
License: MIT License
Project-URL: Repository, https://gitlab.eclipse.org/eclipse-research-labs/nephele-project/wot-py-2.git
Keywords: wot,iot,gateway,fog,w3c
Classifier: Development Status :: 4 - Beta
Classifier: Intended Audience :: Developers
Classifier: Natural Language :: English
Classifier: Operating System :: OS Independent
Classifier: License :: OSI Approved :: MIT License
Classifier: Programming Language :: Python :: 3.9
Classifier: Programming Language :: Python :: 3.10
Classifier: Programming Language :: Python :: 3.11
Classifier: Programming Language :: Python :: 3.12
Classifier: Programming Language :: Python :: 3.13
Requires-Python: >=3.9
License-File: LICENSE
Requires-Dist: tornado<7.0,>=6.5.2
Requires-Dist: jsonschema>=4.25.1
Requires-Dist: reactivex<5.0,>=4.0.4
Requires-Dist: python-slugify>=8.0.4
Requires-Dist: requests-oauthlib<3.0,>=2.0.0
Requires-Dist: pyOpenSSL>=25.1.0
Requires-Dist: aiocoap[linkheader,oscore]>=0.4.7; platform_system != "Darwin"
Requires-Dist: amqtt>=0.10.1
Requires-Dist: eclipse-zenoh>=1.5.0
Requires-Dist: websockets>=15.0.1
Provides-Extra: tests
Requires-Dist: pytest>=8.4.1; extra == "tests"
Requires-Dist: pytest-cov>=6.2.1; extra == "tests"
Requires-Dist: pytest-rerunfailures>=16.0.1; extra == "tests"
Requires-Dist: pytest-asyncio>=1.1.0; extra == "tests"
Requires-Dist: faker>=37.6.0; extra == "tests"
Provides-Extra: docs
Requires-Dist: Sphinx>=7.4.7; extra == "docs"
Requires-Dist: sphinx-rtd-theme>=3.0.2; extra == "docs"
Dynamic: license-file
